{
  "errata_id": "4e33e210a1514136877f6f9834a0987d26e78cec4546a9ff76dd98054bc1c95a",
  "attachments": [],
  "tags": [
    "blooms:3",
    "assignment-type:homework",
    "type:practice",
    "time:medium",
    "book:stax-worldhist",
    "lo:stax-worldhist:A04.4.1",
    "context-cnxmod:03383bb5-3101-4e0d-9426-3fc19c902678",
    "book-slug:world-history-volume-1",
    "module-slug:world-history-volume-1:4-4-the-hebrews"
  ],
  "books": [
    {
      "name": "stax-worldhist",
      "lo": [
        "A04.4.1"
      ]
    }
  ],
  "context": [
    "m00112"
  ]
}