{
  "errata_id": "b002f929e5acc32ca3638926e2a0d3cd9cbc414e2856cb8b032b7fee86642395",
  "attachments": [],
  "tags": [
    "time:short",
    "blooms:2",
    "assignment-type:reading",
    "book:stax-worldhist",
    "lo:stax-worldhist:A13.4.4",
    "context-cnxmod:b6c1d7ab-9df3-42fe-b946-99233cc0fc2e",
    "book-slug:world-history-volume-1",
    "module-slug:world-history-volume-1:13-4-the-crusading-movement"
  ],
  "books": [
    {
      "name": "stax-worldhist",
      "lo": [
        "A13.4.4"
      ]
    }
  ],
  "context": [
    "m00121"
  ]
}